[
  {
    "title": "巨人、開幕投手は菅野智之に決定",
    "description": "巨人が開幕投手に菅野智之を選出。昨シーズンは20勝を挙げ、2年連続で最多勝利投手となった実績を持つ。チームの勝利を導く期待が高い。"
  },
  {
    "title": "DeNA、大和が今季復帰へ",
    "description": "DeNAの大和が今季復帰へ向けて順調なリハビリを進めている。昨シーズンは怪我で出場機会が限られたが、復帰後の活躍が期待される。"
  },
  {
    "title": "中日、若手栗林がブレイク間近",
    "description": "中日の若手栗林が開幕前の調子が絶好調と評判。打撃・守備共に安定感を見せ、ブレイクの兆しが感じられる。今季注目の選手となるか。"
  },
  {
    "title": "阪神、岩崎が先発ローテ入り",
    "description": "阪神が岩崎を先発ローテーションに入れることを決定。岩崎は昨シーズンに不調もあったが、今季は復活を期待されている。"
  },
  {
    "title": "広島、打線に新戦力加入",
    "description": "広島が打撃力強化のため新戦力を獲得。その戦力は昨シーズン打率3割を超え、長打力も優れている。打線の中心になる可能性大。"
  },
  {
    "title": "楽天、ストップ高の好調さ維持",
    "description": "楽天が開幕を迎えて好調なスタートを切った。投手陣・打線ともに安定しており、連勝を重ねている。今後もその勢いを維持するか注目される。"
  },
  {
    "title": "西武、主力選手が故障離脱",
    "description": "西武が主力選手の故障離脱を発表。その選手は昨季23本塁打を記録し、打線の中心だった。代役が求められる状況となっている。"
  },
  {
    "title": "ヤクルト、若手投手が躍進",
    "description": "ヤクルトが若手投手の躍進が目覚ましい。開幕前の調子が絶好調で、先発ローテーション入りも期待される。今季の牽引役になるか注目だ。"
  },
  {
    "title": "オリックス、新外国人選手が契約",
    "description": "オリックスが新たな外国人選手を獲得したことが発表された。その選手は守備力と打撃力を兼ね備え、今季のチーム強化に貢献すると期待されている。"
  },
  {
    "title": "北海道日本ハム、エースが完投勝利",
    "description": "北海道日本ハムのエースが開幕戦で完投勝利を挙げた。圧倒的なピッチングで相手打線を封じ、チームの勝利に貢献した。今季もその好調を維持するか注目される。"
  }
]